present/__init__.py
present/__main__.py
im_present-0.0.1.dist-info/LICENSE.md
im_present-0.0.1.dist-info/METADATA
im_present-0.0.1.dist-info/WHEEL
im_present-0.0.1.dist-info/entry_points.txt
im_present-0.0.1.dist-info/top_level.txt
im_present-0.0.1.dist-info/RECORD
