Metadata-Version: 2.1
Name: im-present
Version: 0.0.1
Summary: Peridoically shake the mouse pointer to prove you're present
Home-page: https://github.com/fastily/im-present
Author: Fastily
Author-email: fastily@users.noreply.github.com
Project-URL: Bug Tracker, https://github.com/fastily/im-present/issues
Classifier: Natural Language :: English
Classifier: Programming Language :: Python :: 3
Classifier: Programming Language :: Python :: 3.11
Classifier: License :: OSI Approved :: GNU General Public License v3 (GPLv3)
Classifier: Operating System :: OS Independent
Requires-Python: >=3.11
License-File: LICENSE.md
Requires-Dist: pyautogui
Requires-Dist: rich
